memoi/__init__.py
memoi/__version__.py
memoi-0.1.0.dist-info/LICENSE
memoi-0.1.0.dist-info/METADATA
memoi-0.1.0.dist-info/WHEEL
memoi-0.1.0.dist-info/entry_points.txt
memoi-0.1.0.dist-info/top_level.txt
memoi-0.1.0.dist-info/RECORD
