Metadata-Version: 2.1
Name: memoi
Version: 0.1.0
Summary: provides generic methods to memoize function and method calls
Home-page: https://github.com/emanuel-schmid/memoi
Author: Emanuel Schmid
Author-email: schmide@ethz.ch
License: GPL-3
Keywords: memoization,cache
Classifier: Programming Language :: Python :: 3
Requires-Python: >=3.10
License-File: LICENSE
Requires-Dist: dateparser
Requires-Dist: pydantic
Provides-Extra: pdf
Requires-Dist: ReportLab >=1.2 ; extra == 'pdf'
Requires-Dist: RXP ; extra == 'pdf'
Provides-Extra: rest
Requires-Dist: docutils >=0.3 ; extra == 'rest'
Requires-Dist: pack ==1.1,==1.3 ; extra == 'rest'
